MANIFEST.in
README.txt
bootstrap.py
buildout.cfg
setup.cfg
setup.py
svnignore
zopeskel.niteoweb.tmproj
docs/HISTORY.txt
docs/svnignore
docs/source/conf.py
docs/source/glossary.rst
docs/source/headquarters.rst
docs/source/index.rst
docs/source/plone_project.rst
docs/source/prelude.rst
docs/source/toolbox.rst
zopeskel/__init__.py
zopeskel.niteoweb.egg-info/PKG-INFO
zopeskel.niteoweb.egg-info/SOURCES.txt
zopeskel.niteoweb.egg-info/dependency_links.txt
zopeskel.niteoweb.egg-info/entry_points.txt
zopeskel.niteoweb.egg-info/namespace_packages.txt
zopeskel.niteoweb.egg-info/not-zip-safe
zopeskel.niteoweb.egg-info/requires.txt
zopeskel.niteoweb.egg-info/top_level.txt
zopeskel/niteoweb/__init__.py
zopeskel/niteoweb/niteoweb.py
zopeskel/niteoweb/templates/niteoweb/+package+.tmproj
zopeskel/niteoweb/templates/niteoweb/README.txt
zopeskel/niteoweb/templates/niteoweb/base.cfg_tmpl
zopeskel/niteoweb/templates/niteoweb/bootstrap.py
zopeskel/niteoweb/templates/niteoweb/development.cfg_tmpl
zopeskel/niteoweb/templates/niteoweb/production.cfg_tmpl
zopeskel/niteoweb/templates/niteoweb/production_with_cronjobs.cfg_tmpl
zopeskel/niteoweb/templates/niteoweb/setup.cfg
zopeskel/niteoweb/templates/niteoweb/setup.py_tmpl
zopeskel/niteoweb/templates/niteoweb/sphinx.cfg_tmpl
zopeskel/niteoweb/templates/niteoweb/svnignore
zopeskel/niteoweb/templates/niteoweb/versions.cfg_tmpl
zopeskel/niteoweb/templates/niteoweb/docs/HISTORY.txt_tmpl
zopeskel/niteoweb/templates/niteoweb/docs/INSTALL.txt
zopeskel/niteoweb/templates/niteoweb/docs/LICENSE.GPL
zopeskel/niteoweb/templates/niteoweb/docs/LICENSE.txt_tmpl
zopeskel/niteoweb/templates/niteoweb/docs/svnignore
zopeskel/niteoweb/templates/niteoweb/docs/source/conf.py_tmpl
zopeskel/niteoweb/templates/niteoweb/docs/source/index.rst_tmpl
zopeskel/niteoweb/templates/niteoweb/etc/iptables_tmpl
zopeskel/niteoweb/templates/niteoweb/etc/svnignore
zopeskel/niteoweb/templates/niteoweb/etc_templates/fabfile.py.in_tmpl
zopeskel/niteoweb/templates/niteoweb/etc_templates/munin-node.conf.in_tmpl
zopeskel/niteoweb/templates/niteoweb/etc_templates/nginx.conf.in_tmpl
zopeskel/niteoweb/templates/niteoweb/keys/Kunta.pub
zopeskel/niteoweb/templates/niteoweb/keys/iElectric.pub
zopeskel/niteoweb/templates/niteoweb/keys/zupo.pub
