Metadata-Version: 1.0
Name: zopeskel.niteoweb
Version: 0.1
Summary: Paster templates for standard NiteoWeb Plone projects
Home-page: http://pypi.python.org/pypi/zopeskel.niteoweb
Author: NiteoWeb Ltd.
Author-email: info@niteoweb.com
License: GPL
Keywords: plone zopeskel
Platform: UNKNOWN
Classifier: Programming Language :: Python
Classifier: Framework :: Plone
